LICENSE
README.md
pyproject.toml
setup.cfg
setup.py
pygsod/__init__.py
pygsod/constants.py
pygsod/epw_converter.py
pygsod/gsod.py
pygsod/isd_lite.py
pygsod/isdhistory.py
pygsod/ish_full.py
pygsod/noaadata.py
pygsod/output.py
pygsod/tmy_download.py
pygsod/utils.py
pygsod.egg-info/PKG-INFO
pygsod.egg-info/SOURCES.txt
pygsod.egg-info/dependency_links.txt
pygsod.egg-info/requires.txt
pygsod.egg-info/top_level.txt
support/__init__.py