Metadata-Version: 2.1
Name: pygsod
Version: 0.2.4
Summary: A Wrapper to Download data off NOAA's Global Summary of the day,and load them into pandas
Home-page: https://effibem.com
Author: Julien Marrec & EffiBEM
Author-email: contact@effibem.com
License: MIT
Project-URL: Bug Tracker, https://github.com/jmarrec/pygsod/issues
Project-URL: Source Code, https://github.com/jmarrec/pygsod
Keywords: gsod weather python pandas epw energyplus
Platform: UNKNOWN
Classifier: Development Status :: 3 - Alpha
Classifier: Natural Language :: English
Classifier: Environment :: Console
Classifier: Intended Audience :: Science/Research
Classifier: Operating System :: OS Independent
Classifier: Topic :: Scientific/Engineering
Classifier: License :: OSI Approved :: MIT License
Classifier: Programming Language :: Python :: 3
Provides-Extra: dev
Provides-Extra: test
